setup.py
on_http_api2_0/__init__.py
on_http_api2_0/api_client.py
on_http_api2_0/configuration.py
on_http_api2_0/rest.py
on_http_api2_0.egg-info/PKG-INFO
on_http_api2_0.egg-info/SOURCES.txt
on_http_api2_0.egg-info/dependency_links.txt
on_http_api2_0.egg-info/requires.txt
on_http_api2_0.egg-info/top_level.txt
on_http_api2_0/apis/__init__.py
on_http_api2_0/apis/api_api.py
on_http_api2_0/models/__init__.py
on_http_api2_0/models/action.py
on_http_api2_0/models/error.py
on_http_api2_0/models/error_response.py
on_http_api2_0/models/generic_obj.py
on_http_api2_0/models/get_user_obj.py
on_http_api2_0/models/hooks_2_0_hook_base.py
on_http_api2_0/models/hooks_2_0_hook_post.py
on_http_api2_0/models/inline_response_200.py
on_http_api2_0/models/ipmi_obm_service_obm.py
on_http_api2_0/models/ipmiobmservice_obm_config.py
on_http_api2_0/models/lookups_2_0_lookup_base.py
on_http_api2_0/models/node_2_0_get_node.py
on_http_api2_0/models/node_2_0_partial_node.py
on_http_api2_0/models/nodes_post_obm_by_id.py
on_http_api2_0/models/obm.py
on_http_api2_0/models/obm_led.py
on_http_api2_0/models/patch_user_obj.py
on_http_api2_0/models/poller_2_0_partial_poller.py
on_http_api2_0/models/post_node_workflow.py
on_http_api2_0/models/post_node_workflow_options.py
on_http_api2_0/models/post_tags.py
on_http_api2_0/models/post_tasks.py
on_http_api2_0/models/post_workflow.py
on_http_api2_0/models/post_workflow_options.py
on_http_api2_0/models/post_workflow_options_defaults.py
on_http_api2_0/models/relations_obj.py
on_http_api2_0/models/role_obj.py
on_http_api2_0/models/skus_2_0_skus_upsert.py
on_http_api2_0/models/ssh_ibm_service_ibm.py
on_http_api2_0/models/sshibmservice_ibm_config.py
on_http_api2_0/models/tag_rule.py
on_http_api2_0/models/user_obj.py
on_http_api2_0/models/versions_response.py
on_http_api2_0/models/workflow_graph.py
on_http_api2_0/models/workflow_graph_task.py
on_http_api2_0/models/workflow_task.py