Metadata-Version: 1.0
Name: on-http-api2-0
Version: 1.0.11
Summary: rackhd api
Home-page: UNKNOWN
Author: UNKNOWN
Author-email: UNKNOWN
License: UNKNOWN
Keywords: Swagger,rackhd api
Platform: UNKNOWN
